cfnmatch.cpython-38-x86_64-linux-gnu.so
cfnmatch-1.0.0.dist-info/top_level.txt
cfnmatch-1.0.0.dist-info/METADATA
cfnmatch-1.0.0.dist-info/WHEEL
cfnmatch-1.0.0.dist-info/RECORD
